pyclamp/DataModel.py
pyclamp/PyQtTreeModel.py
pyclamp/__init__.py
pyclamp/__main__.py
pyclamp/heka_reader.py
pyclamp/pyCLAMP.py
pyclamp-0.0.2.dist-info/LICENSE
pyclamp-0.0.2.dist-info/METADATA
pyclamp-0.0.2.dist-info/WHEEL
pyclamp-0.0.2.dist-info/top_level.txt
pyclamp-0.0.2.dist-info/RECORD
