Metadata-Version: 2.1
Name: pyclamp
Version: 0.0.2
Summary: Time series recordings analysis in Python with UI similar to pCLAMP.
Home-page: https://github.com/marcel-goldschen-ohm/pyCLAMP
Download-URL: 
Author: Marcel Goldschen-Ohm
Author-email: goldschen-ohm@utexas.edu
Maintainer: Marcel Goldschen-Ohm
Maintainer-email: goldschen-ohm@utexas.edu
License: MIT
Classifier: Development Status :: 3 - Alpha
Classifier: Intended Audience :: Science/Research
Classifier: License :: OSI Approved :: MIT License
Classifier: Natural Language :: English
Classifier: Operating System :: OS Independent
Classifier: Programming Language :: Python :: 3
Classifier: Topic :: Scientific/Engineering
License-File: LICENSE
Requires-Dist: PyQt6
Requires-Dist: numpy
Requires-Dist: scipy
Requires-Dist: lmfit
Requires-Dist: pyqtgraph
Requires-Dist: qtawesome
